datavalidator/__init__.py
datavalidator/validator.py
simon_datavalidator-0.11.dist-info/METADATA
simon_datavalidator-0.11.dist-info/WHEEL
simon_datavalidator-0.11.dist-info/top_level.txt
simon_datavalidator-0.11.dist-info/RECORD
