Metadata-Version: 2.1
Name: simon-datavalidator
Version: 0.11
Summary: A simple data validation package
Home-page: https://github.com/Data-Epic/data-validator-Simon-Dickson.git
Author: Simon Dickson
Author-email: simonoche987@gmail.com
Classifier: Programming Language :: Python :: 3
Classifier: License :: OSI Approved
Classifier: Operating System :: OS Independent
